CHANGELOG.md
gitlab_deployment_changelog/__version__.py
gitlab_deployment_changelog/gdc.py
gitlab_deployment_changelog/utils/__init__.py
gitlab_deployment_changelog/utils/gitlab_connector.py
gitlab_deployment_changelog/utils/slack.py
gitlab_deployment_changelog-0.2.0.dist-info/entry_points.txt
gitlab_deployment_changelog-0.2.0.dist-info/WHEEL
gitlab_deployment_changelog-0.2.0.dist-info/METADATA
gitlab_deployment_changelog-0.2.0.dist-info/RECORD
