Metadata-Version: 2.1
Name: gitlab-deployment-changelog
Version: 0.2.0
Summary: Gitlab Deployment Changelog Creator
License: MIT
Author-email: Christoph Becker <christoph.becker@exb.de>,Lukas Jesche <lukas.jesche@exb.de>,Riccardo Padoan <riccardo.padoan@exb.de>
Requires-Python: >=3.10
Requires-Dist: loguru>=0.7.2
Requires-Dist: pytest-mock>=3.12.0
Requires-Dist: python-decouple>=3.8
Requires-Dist: python-gitlab>=4.1.1
Requires-Dist: pyyaml>=6.0.1
Requires-Dist: requests>=2.31.0
Project-URL: Changelog, https://github.com/ExB-Group/gitlab-deployment-changelog/blob/main/CHANGELOG.md
Project-URL: Homepage, https://github.com/ExB-Group/gitlab-deployment-changelog
Project-URL: Repository, https://github.com/ExB-Group/gitlab-deployment-changelog
